udemy/__init__.py
udemy/api.py
udemy/errors.py
udemy/models.py
udemy_python-0.0.3.dist-info/LICENSE
udemy_python-0.0.3.dist-info/METADATA
udemy_python-0.0.3.dist-info/WHEEL
udemy_python-0.0.3.dist-info/top_level.txt
udemy_python-0.0.3.dist-info/RECORD
