Metadata-Version: 2.1
Name: udemy-python
Version: 0.0.3
Summary: A python wrapper for the Udemy Instructor API
Home-page: https://github.com/anthonyebiner/Python-Udemy
Author: Anthony Ebiner
Author-email: anthonyebiner@gmail.com
License: UNKNOWN
Platform: UNKNOWN
Classifier: Programming Language :: Python :: 3
Classifier: License :: OSI Approved :: MIT License
Classifier: Operating System :: OS Independent
Requires-Python: >=3.6
Requires-Dist: requests
